README.md
setup.py
yt_video_viewer/__init__.py
yt_video_viewer.egg-info/PKG-INFO
yt_video_viewer.egg-info/SOURCES.txt
yt_video_viewer.egg-info/dependency_links.txt
yt_video_viewer.egg-info/requires.txt
yt_video_viewer.egg-info/top_level.txt