Metadata-Version: 2.1
Name: yt-video-viewer
Version: 1.0.0
Summary: A python library to watch video on youtube automatically.
Home-page: https://youtube-api.datakund.com/en/latest/
Author: DataKund
Author-email: datakund@gmail.com
License: Apache License 2.0
Keywords: youtube python btstudio automation video view watch login
Platform: UNKNOWN
